odoo/addons/easy_my_coop_sponsorship/__init__.py
odoo/addons/easy_my_coop_sponsorship/__manifest__.py
odoo/addons/easy_my_coop_sponsorship/models/__init__.py
odoo/addons/easy_my_coop_sponsorship/models/res_partner.py
odoo/addons/easy_my_coop_sponsorship/models/subscription_request.py
odoo/addons/easy_my_coop_sponsorship/tests/__init__.py
odoo/addons/easy_my_coop_sponsorship/tests/test_member_wizard.py
odoo/addons/easy_my_coop_sponsorship/tests/test_subscription.py
odoo/addons/easy_my_coop_sponsorship/views/menus.xml
odoo/addons/easy_my_coop_sponsorship/views/res_partner_view.xml
odoo/addons/easy_my_coop_sponsorship/views/subscription_request_view.xml
odoo/addons/easy_my_coop_sponsorship/wizard/__init__.py
odoo/addons/easy_my_coop_sponsorship/wizard/sponsee_member_wizard.py
odoo/addons/easy_my_coop_sponsorship/wizard/sponsee_member_wizard.xml
odoo12_addon_easy_my_coop_sponsorship-12.0.0.0.2.dist-info/METADATA
odoo12_addon_easy_my_coop_sponsorship-12.0.0.0.2.dist-info/WHEEL
odoo12_addon_easy_my_coop_sponsorship-12.0.0.0.2.dist-info/top_level.txt
odoo12_addon_easy_my_coop_sponsorship-12.0.0.0.2.dist-info/RECORD
