Metadata-Version: 2.1
Name: odoo12-addon-easy-my-coop-sponsorship
Version: 12.0.0.0.2
Summary: Odoo Sponsorship module for Easy My Coop cooperative addons
Home-page: https://coopdevs.org
Author: Coopdevs Treball SCCL
License: AGPL-3
Platform: UNKNOWN
Classifier: Programming Language :: Python
Classifier: Framework :: Odoo
Classifier: License :: OSI Approved :: GNU Affero General Public License v3
Requires-Python: >=3.5
Requires-Dist: odoo12-addon-easy-my-coop
Requires-Dist: odoo (<12.1dev,>=12.0a)
